djangotools/__init__.py
djangotools/apps.py
djangotools/decorators/OnlyAuthorAccess.py
djangotools/decorators/__init__.py
djangotools/extra/__init__.py
djangotools/extra/getFirstKwarg.py
djangotools/migrations/__init__.py
djangotools/mixins/AdministratorAndOnlyAuthorAccess.py
djangotools/mixins/OnlyAdministratorAccess.py
djangotools/mixins/OnlyAuthorAccess.py
djangotools/mixins/__init__.py
djangotools-2.2.2.dist-info/License
djangotools-2.2.2.dist-info/METADATA
djangotools-2.2.2.dist-info/WHEEL
djangotools-2.2.2.dist-info/top_level.txt
djangotools-2.2.2.dist-info/RECORD
